coin2086/__init__.py
coin2086/bitstamp.py
coin2086/pnl.py
coin2086/pricedownload.py
coin2086/validation.py
coin2086/valuation.py
coin2086-0.1.3.dist-info/LICENSE
coin2086-0.1.3.dist-info/WHEEL
coin2086-0.1.3.dist-info/METADATA
coin2086-0.1.3.dist-info/RECORD
