Metadata-Version: 2.1
Name: coin2086
Version: 0.1.3
Summary: French Crypto Taxes Made Easy
Home-page: https://github.com/fandre90/coin2086
License: MIT
Keywords: cryptocurrency,accounting,tax
Author: Fabien André
Author-email: fabien.andre90@gmail.com
Requires-Python: >=3.6.2,<4.0
Classifier: Development Status :: 4 - Beta
Classifier: License :: OSI Approved :: MIT License
Classifier: Operating System :: OS Independent
Classifier: Programming Language :: Python :: 3
Classifier: Programming Language :: Python :: 3.7
Classifier: Programming Language :: Python :: 3.8
Classifier: Programming Language :: Python :: 3.9
Classifier: Topic :: Office/Business :: Financial
Classifier: Topic :: Software Development :: Libraries
Requires-Dist: pandas (>=1.1,<2.0)
Requires-Dist: requests (>=2.10,<3.0)
Project-URL: Documentation, https://coin2086.readthedocs.io/
Project-URL: Repository, https://github.com/fandre90/coin2086
